setup.py
django_filebrowser_django13.egg-info/PKG-INFO
django_filebrowser_django13.egg-info/SOURCES.txt
django_filebrowser_django13.egg-info/dependency_links.txt
django_filebrowser_django13.egg-info/not-zip-safe
django_filebrowser_django13.egg-info/top_level.txt
filebrowser/__init__.py
filebrowser/base.py
filebrowser/decorators.py
filebrowser/fields.py
filebrowser/forms.py
filebrowser/functions.py
filebrowser/models.py
filebrowser/settings.py
filebrowser/urls.py
filebrowser/views.py
filebrowser/management/__init__.py
filebrowser/management/commands/__init__.py
filebrowser/management/commands/version_generator.py
filebrowser/templatetags/__init__.py
filebrowser/templatetags/fb_csrf.py
filebrowser/templatetags/fb_pagination.py
filebrowser/templatetags/fb_tags.py
filebrowser/templatetags/fb_versions.py