Metadata-Version: 1.0
Name: django-filebrowser-django13
Version: 3.0
Summary: Media-Management with the Django Admin-Interface. Package for using without django-grapelli in Django 1.3
Home-page: http://github.com/msaelices/django-filebrowser-no-grappelli-for-django13
Author: Patrick Kranzlmueller
Author-email: patrick@vonautomatisch.at
License: UNKNOWN
Platform: UNKNOWN
Classifier: Development Status :: 4 - Beta
Classifier: Environment :: Web Environment
Classifier: Intended Audience :: Developers
Classifier: License :: OSI Approved :: BSD License
Classifier: Operating System :: OS Independent
Classifier: Programming Language :: Python
Classifier: Framework :: Django
